nati_log/__init__.py
nati_log/client.py
nati_log/middleware.py
tests/__init__.py
tests/settings.py
tests/test_client.py
tests/test_middleware.py
nati_log-2.2.4.dist-info/METADATA
nati_log-2.2.4.dist-info/WHEEL
nati_log-2.2.4.dist-info/top_level.txt
nati_log-2.2.4.dist-info/RECORD
