Metadata-Version: 2.1
Name: nati-log
Version: 2.2.4
Summary: Librería para interactuar con la API de NatiLog
Home-page: UNKNOWN
Author: Natalí
Author-email: UNKNOWN
License: UNKNOWN
Platform: UNKNOWN
Requires-Dist: requests>=2.25.1
